CHANGES.txt
CONTRIBUTORS.txt
MANIFEST.in
README.rst
bootstrap.py
setup.cfg
setup.py
docs/LICENSE.GPL
docs/LICENSE.txt
src/collective/__init__.py
src/collective.stomach.egg-info/PKG-INFO
src/collective.stomach.egg-info/SOURCES.txt
src/collective.stomach.egg-info/dependency_links.txt
src/collective.stomach.egg-info/entry_points.txt
src/collective.stomach.egg-info/namespace_packages.txt
src/collective.stomach.egg-info/not-zip-safe
src/collective.stomach.egg-info/requires.txt
src/collective.stomach.egg-info/top_level.txt
src/collective/stomach/__init__.py
src/collective/stomach/configure.zcml
src/collective/stomach/testing.py
src/collective/stomach/browser/__init__.py
src/collective/stomach/browser/configure.zcml
src/collective/stomach/browser/stomachview.pt
src/collective/stomach/browser/stomachview.py
src/collective/stomach/interfaces/__init__.py
src/collective/stomach/interfaces/stomachlayer.py
src/collective/stomach/profiles/default/browserlayer.xml
src/collective/stomach/profiles/default/metadata.xml
src/collective/stomach/profiles/default/registry.xml
src/collective/stomach/tests/__init__.py
src/collective/stomach/tests/test_view.py