Metadata-Version: 1.1
Name: collective.stomach
Version: 0.2
Summary: This products is used to see which eggs are in Plone site.
Home-page: https://github.com/collective/collective.stomach
Author: Benoit Suttor
Author-email: bsuttor@cirb.irisnet.be
License: gpl
Platform: UNKNOWN
Classifier: Environment :: Web Environment
Classifier: Operating System :: OS Independent
Classifier: Framework :: Zope2
Classifier: Framework :: Plone
Classifier: Framework :: Plone :: 4.2
Classifier: Framework :: Plone :: 4.3
Classifier: Programming Language :: Python
Classifier: Programming Language :: Python :: 2.6
Classifier: Programming Language :: Python :: 2.7
Classifier: Topic :: Software Development :: Libraries :: Python Modules
